vibe/__init__.py
vibe/__main__.py
vibe/form_context.py
vibe/ir.py
vibe/main.py
show_me_your_vibe-0.1.0.dist-info/LICENSE
show_me_your_vibe-0.1.0.dist-info/METADATA
show_me_your_vibe-0.1.0.dist-info/WHEEL
show_me_your_vibe-0.1.0.dist-info/entry_points.txt
show_me_your_vibe-0.1.0.dist-info/RECORD
