Metadata-Version: 2.3
Name: show-me-your-vibe
Version: 0.1.0
Summary: Simple CLI tool to generate context for LLMs from codebase
License: MIT
Keywords: cli,llm,context,prompt,developer-tools
Author: Skylar V. Allen
Author-email: vladimir@alinsky.tech
Requires-Python: >=3.10
Classifier: Development Status :: 5 - Production/Stable
Classifier: Environment :: Console
Classifier: Intended Audience :: Developers
Classifier: License :: OSI Approved :: MIT License
Classifier: Operating System :: OS Independent
Classifier: Programming Language :: Python :: 3
Classifier: Programming Language :: Python :: 3.10
Classifier: Programming Language :: Python :: 3.11
Classifier: Programming Language :: Python :: 3.12
Classifier: Programming Language :: Python :: 3.13
Classifier: Programming Language :: Python :: 3.14
Classifier: Programming Language :: Python :: 3.15
Classifier: Topic :: Utilities
Requires-Dist: gitpython (>=3.1.45,<4.0.0)
Requires-Dist: pydantic (>=2.11.7,<3.0.0)
Requires-Dist: pyperclip (>=1.9.0,<2.0.0)
Requires-Dist: typer (>=0.17.4,<0.18.0)
Project-URL: Homepage, https://github.com/SKY-ALIN/vibe
Project-URL: Issues, https://github.com/SKY-ALIN/vibe/issues
Project-URL: Repository, https://github.com/SKY-ALIN/vibe
